humancursor_botasaurus/__init__.py
humancursor_botasaurus/web_cursor.py
humancursor_playwright/__init__.py
humancursor_playwright/playwright_cursor.py
humancursor_playwright/utilities/__init__.py
humancursor_playwright/utilities/calculate_and_randomize.py
humancursor_playwright/utilities/human_curve_generator.py
humancursor_playwright/utilities/playwright_adjuster.py
humancursor_playwright-0.1.1.dist-info/licenses/LICENSE
humancursor_playwright-0.1.1.dist-info/METADATA
humancursor_playwright-0.1.1.dist-info/WHEEL
humancursor_playwright-0.1.1.dist-info/top_level.txt
humancursor_playwright-0.1.1.dist-info/RECORD
