Metadata-Version: 2.4
Name: humancursor-playwright
Version: 0.1.1
Summary: A Playwright adaptation of HumanCursor for human-like mouse movements
Home-page: https://github.com/yourusername/humancursor-playwright
Author: HumanCursor Playwright Fork
Author-email: example@example.com
Project-URL: Bug Reports, https://github.com/yourusername/humancursor-playwright/issues
Project-URL: Source, https://github.com/yourusername/humancursor-playwright
Project-URL: Original HumanCursor, https://github.com/zajcikk/HumanCursor
Project-URL: HumanCursor-Botasaurus, https://github.com/youroriginalrepo/humancursor-botasaurus
Keywords: playwright automation human cursor mouse movement web testing
Classifier: Development Status :: 4 - Beta
Classifier: Intended Audience :: Developers
Classifier: Topic :: Software Development :: Testing
Classifier: Topic :: Internet :: WWW/HTTP :: Browsers
Classifier: License :: OSI Approved :: MIT License
Classifier: Operating System :: OS Independent
Classifier: Programming Language :: Python :: 3
Classifier: Programming Language :: Python :: 3.8
Classifier: Programming Language :: Python :: 3.9
Classifier: Programming Language :: Python :: 3.10
Classifier: Programming Language :: Python :: 3.11
Classifier: Programming Language :: Python :: 3.12
Requires-Python: >=3.8
License-File: LICENSE
Requires-Dist: playwright>=1.30.0
Requires-Dist: numpy>=1.19.0
Requires-Dist: pytweening>=1.0.4
Provides-Extra: dev
Requires-Dist: pytest>=7.0.0; extra == "dev"
Requires-Dist: pytest-asyncio>=0.21.0; extra == "dev"
Requires-Dist: black>=22.0.0; extra == "dev"
Requires-Dist: flake8>=4.0.0; extra == "dev"
Dynamic: author
Dynamic: author-email
Dynamic: classifier
Dynamic: description
Dynamic: description-content-type
Dynamic: home-page
Dynamic: keywords
Dynamic: license-file
Dynamic: project-url
Dynamic: provides-extra
Dynamic: requires-dist
Dynamic: requires-python
Dynamic: summary
